{
  "en": {
    "ui.language": "Language",
    "ui.version": "Version: {version}",
    "ui.start": "Start experience",
    "ui.retry": "Retry start",
    "ui.active": "Experience active",
    "ui.enterAr": "Enter AR",
    "ui.exitAr": "Exit AR",
    "ui.about": "About",
    "ui.close": "Close",
    "ui.following": "Following",
    "ui.recenter": "Recenter",
    "ui.starting": "Starting...",
    "status.tapStart": "Tap start to request camera, location, and orientation.",
    "status.requestingPermissions": "Requesting camera, location, and orientation permissions...",
    "status.liveTracking": "Live position tracking active.",
    "status.orientationUnavailable": "Camera and location active. Device orientation unavailable/denied, live-view arrows disabled.",
    "status.orientationActive": "Camera, location, and orientation active. If arrows are missing, rotate device to initialize compass.",
    "status.locationUnavailableArOk": "Camera active. Location unavailable ({error}). AR can still be launched.",
    "status.setupFailed": "Setup failed: {error}.{hint}",
    "status.xrEnded": "Immersive AR session ended.",
    "status.xrWaitingLocation": "Immersive AR session active. Waiting for location to place target arrows.",
    "status.xrActive": "Immersive AR session active.",
    "status.xrApproxHeading": "Immersive AR active with approximate heading (next step is ahead).",
    "status.webxrUnavailable": "WebXR is not available on this browser/device.",
    "status.failedStartAr": "Failed to start AR: {error}. On Quest, enable Experimental Features for WebXR/Passthrough and confirm camera permission.",
    "status.locationError": "Location error: {error}",
    "geo.unableRead": "Unable to read location.",
    "geo.permissionDenied": "Location permission denied by browser/device settings.",
    "geo.positionUnavailable": "Location unavailable on this device right now.",
    "geo.timeout": "Location request timed out before first fix.",
    "hint.httpsRequired": " HTTPS is required for geolocation.",
    "hint.questLocation": " On Quest, also verify headset Location Services are enabled.",
    "distance.noFix": "No location fix yet.",
    "distance.locationUnavailable": "Location unavailable: target distance and position are paused.",
    "distance.journeyComplete": "Journey complete.",
    "distance.waitingNextStep": "Next step: waiting for location.",
    "distance.nextStep": "Next step: {id} at {distance}",
    "distance.insideNextStep": "Inside next step {id} zone ({radius}m)",
    "journey.notConfigured": "Journey: not configured.",
    "journey.complete": "{name}: complete (remaining {remaining} | planned {planned})",
    "journey.progress": "{name}: step {step}/{total}, next {next}, remaining {remaining}, planned {planned}",
    "xr.summaryChecking": "Checking WebXR support...",
    "xr.summaryUnavailable": "WebXR AR: not available on this device/browser.",
    "xr.summarySupported": "WebXR AR: supported. You can launch immersive AR with Enter AR.",
    "xr.summaryTryAr": "WebXR is available. AR support may require Quest experimental flags; you can still try Enter AR.",
    "xr.summaryUncertain": "WebXR check uncertain ({error}). You can still try Enter AR.",
    "xr.summaryDomOverlayOn": "WebXR DOM overlay active in AR session.",
    "xr.summaryDomOverlayOff": "DOM overlay unavailable on this AR session: OpenStreetMap panel cannot be shown in-headset.",
    "about.codedWithLabel": "Coded with",
    "about.licenseLabel": "License:",
    "about.mapDataLabel": "Map data:",
    "about.mapLibraryLabel": "Map library:",
    "about.xrLibraryLabel": "3D/XR library:",
    "about.favicon": "Favicon source:"
    ,
    "confidence.high": "HIGH",
    "confidence.med": "MED",
    "confidence.low": "LOW",
    "confidence.noLocation": "No location",
    "confidence.stable": "Stable sensors",
    "confidence.someDrift": "Some drift",
    "confidence.stale": "Stale heading/location",
    "turn.ahead": "Ahead",
    "turn.left": "{deg}\u00b0 left",
    "turn.right": "{deg}\u00b0 right",
    "heading.compass": "Compass",
    "heading.fallback": "Fallback",
    "xr.nextWaiting": "Next step: waiting for location",
    "xr.nextComplete": "Next step: journey complete",
    "xr.distanceUnknown": "Distance: --",
    "xr.distanceZero": "Distance: 0 m",
    "xr.turnUnknown": "Turn: -- | Heading: --",
    "xr.lineDistance": "Distance: {distance} | Remaining: {remaining}",
    "xr.lineTurn": "Turn: {turn} | Heading: {heading} | Planned: {planned} | {confidence}",
    "xr.lineNext": "Next step: {id}{inRange}",
    "xr.inRangeSuffix": " (IN RANGE)"
  },
  "fr": {
    "ui.language": "Langue",
    "ui.version": "Version : {version}",
    "ui.start": "Démarrer",
    "ui.retry": "Réessayer",
    "ui.active": "Expérience active",
    "ui.enterAr": "Entrer en AR",
    "ui.exitAr": "Quitter AR",
    "ui.about": "À propos",
    "ui.close": "Fermer",
    "ui.following": "Suivi",
    "ui.recenter": "Recentrer",
    "ui.starting": "Démarrage...",
    "status.tapStart": "Touchez Démarrer pour autoriser la caméra, la position et l'orientation.",
    "status.requestingPermissions": "Demande des autorisations caméra, position et orientation...",
    "status.liveTracking": "Suivi de position en direct actif.",
    "status.orientationUnavailable": "Caméra et position actives. Orientation indisponible/refusée, flèches caméra désactivées.",
    "status.orientationActive": "Caméra, position et orientation actives. Si les flèches manquent, tournez l'appareil pour initialiser la boussole.",
    "status.locationUnavailableArOk": "Caméra active. Position indisponible ({error}). L'AR peut quand même être lancée.",
    "status.setupFailed": "Échec de configuration : {error}.{hint}",
    "status.xrEnded": "Session AR immersive terminée.",
    "status.xrWaitingLocation": "Session AR immersive active. En attente de la position pour placer les flèches.",
    "status.xrActive": "Session AR immersive active.",
    "status.xrApproxHeading": "AR immersive active avec cap approximatif (la prochaine étape est devant).",
    "status.webxrUnavailable": "WebXR n'est pas disponible sur cet appareil/navigateur.",
    "status.failedStartAr": "Échec du lancement AR : {error}. Sur Quest, activez les options expérimentales WebXR/Passthrough et vérifiez l'autorisation caméra.",
    "status.locationError": "Erreur de position : {error}",
    "geo.unableRead": "Impossible de lire la position.",
    "geo.permissionDenied": "Autorisation de position refusée par le navigateur/appareil.",
    "geo.positionUnavailable": "Position indisponible sur cet appareil pour le moment.",
    "geo.timeout": "La demande de position a expiré avant le premier fix.",
    "hint.httpsRequired": " HTTPS est requis pour la géolocalisation.",
    "hint.questLocation": " Sur Quest, vérifiez aussi que les services de localisation du casque sont activés.",
    "distance.noFix": "Pas encore de position.",
    "distance.locationUnavailable": "Position indisponible : distance et position des cibles en pause.",
    "distance.journeyComplete": "Parcours terminé.",
    "distance.waitingNextStep": "Prochaine étape : en attente de la position.",
    "distance.nextStep": "Prochaine étape : {id} à {distance}",
    "distance.insideNextStep": "Dans la zone de la prochaine étape {id} ({radius} m)",
    "journey.notConfigured": "Parcours : non configuré.",
    "journey.complete": "{name} : terminé (reste {remaining} | planifié {planned})",
    "journey.progress": "{name} : étape {step}/{total}, prochaine {next}, reste {remaining}, planifié {planned}",
    "xr.summaryChecking": "Vérification du support WebXR...",
    "xr.summaryUnavailable": "WebXR AR : indisponible sur cet appareil/navigateur.",
    "xr.summarySupported": "WebXR AR : supporté. Vous pouvez lancer l'AR immersive avec Entrer en AR.",
    "xr.summaryTryAr": "WebXR est disponible. Le support AR peut nécessiter des options expérimentales Quest ; vous pouvez quand même essayer Entrer en AR.",
    "xr.summaryUncertain": "Vérification WebXR incertaine ({error}). Vous pouvez quand même essayer Entrer en AR.",
    "xr.summaryDomOverlayOn": "Superposition DOM WebXR active en session AR.",
    "xr.summaryDomOverlayOff": "Superposition DOM indisponible dans cette session AR : la carte OpenStreetMap ne peut pas s'afficher dans le casque.",
    "about.codedWithLabel": "Codé avec",
    "about.licenseLabel": "Licence :",
    "about.mapDataLabel": "Données cartographiques :",
    "about.mapLibraryLabel": "Bibliothèque cartographique :",
    "about.xrLibraryLabel": "Bibliothèque 3D/XR :",
    "about.favicon": "Source du favicon :"
    ,
    "confidence.high": "ÉLEVÉ",
    "confidence.med": "MOYEN",
    "confidence.low": "FAIBLE",
    "confidence.noLocation": "Pas de position",
    "confidence.stable": "Capteurs stables",
    "confidence.someDrift": "Léger drift",
    "confidence.stale": "Cap/position obsolètes",
    "turn.ahead": "Devant",
    "turn.left": "{deg}\u00b0 à gauche",
    "turn.right": "{deg}\u00b0 à droite",
    "heading.compass": "Boussole",
    "heading.fallback": "Approx.",
    "xr.nextWaiting": "Prochaine étape : en attente de la position",
    "xr.nextComplete": "Prochaine étape : parcours terminé",
    "xr.distanceUnknown": "Distance : --",
    "xr.distanceZero": "Distance : 0 m",
    "xr.turnUnknown": "Direction : -- | Cap : --",
    "xr.lineDistance": "Distance : {distance} | Reste : {remaining}",
    "xr.lineTurn": "Direction : {turn} | Cap : {heading} | Planifié : {planned} | {confidence}",
    "xr.lineNext": "Prochaine étape : {id}{inRange}",
    "xr.inRangeSuffix": " (DANS LA ZONE)"
  }
}
